excellentpandas.py
excellentpandas-0.1.1.dist-info/LICENSE
excellentpandas-0.1.1.dist-info/METADATA
excellentpandas-0.1.1.dist-info/WHEEL
excellentpandas-0.1.1.dist-info/top_level.txt
excellentpandas-0.1.1.dist-info/RECORD
