Metadata-Version: 2.1
Name: excellentpandas
Version: 0.1.1
Summary: Load pandas DataFrames in Excel
Home-page: https://github.com/kinverarity1/excellentpandas
License: UNKNOWN
Platform: UNKNOWN
Requires-Dist: xlwings
Requires-Dist: pandas
